energicast/__init__.py
energicast/backtest.py
energicast/cli.py
energicast/config.py
energicast/pipeline.py
energicast/utils.py
energicast/automl/__init__.py
energicast/automl/search.py
energicast/automl/validation.py
energicast/bench/__init__.py
energicast/bench/openstef.py
energicast/data/__init__.py
energicast/data/entsoe.py
energicast/data/pv.py
energicast/data/weather.py
energicast/deploy/__init__.py
energicast/deploy/export.py
energicast/features/__init__.py
energicast/features/energy.py
energicast/hier/__init__.py
energicast/hier/reconcile.py
energicast/impute/__init__.py
energicast/impute/synth.py
energicast/metrics/__init__.py
energicast/metrics/metrics.py
energicast/models/__init__.py
energicast/models/arima.py
energicast/models/registry.py
energicast/models/tft.py
energicast/models/xgb.py
energicast/scenarios/__init__.py
energicast/scenarios/weather_ensemble.py
energicast-1.0.0.dist-info/licenses/LICENSE
energicast-1.0.0.dist-info/METADATA
energicast-1.0.0.dist-info/WHEEL
energicast-1.0.0.dist-info/entry_points.txt
energicast-1.0.0.dist-info/top_level.txt
energicast-1.0.0.dist-info/RECORD
