Metadata-Version: 2.4
Name: energicast
Version: 1.0.0
Summary: Domain-specific AutoML library for energy forecasting with physics–ML hybrids and synthetic gap filling
Author: dr Tymoteusz Miller, dr inż. Ewelina Kostecka
License: MIT License
Project-URL: Homepage, https://github.com/TyMill/energicast
Project-URL: Documentation, https://tymill.github.io/EnergiCast/
Project-URL: Issues, https://github.com/TyMill/energicast/issues
Project-URL: Changelog, https://github.com/TyMill/energicast/blob/main/CHANGELOG.md
Keywords: energy forecasting,automl,machine learning,time series,renewable energy,load forecasting,pv forecasting,wind forecasting,probabilistic forecasting,hierarchical forecasting,backtesting,feature engineering,quantile regression,reconciliation,mint,pvlib,optuna,xgboost,arima,ets
Classifier: Development Status :: 4 - Beta
Classifier: Intended Audience :: Science/Research
Classifier: Topic :: Scientific/Engineering
Classifier: Topic :: Scientific/Engineering :: Artificial Intelligence
Classifier: Topic :: Scientific/Engineering :: Information Analysis
Classifier: Topic :: Scientific/Engineering :: Physics
Classifier: License :: OSI Approved :: MIT License
Classifier: Programming Language :: Python :: 3
Classifier: Programming Language :: Python :: 3.9
Classifier: Programming Language :: Python :: 3.10
Classifier: Programming Language :: Python :: 3.11
Classifier: Programming Language :: Python :: 3.12
Requires-Python: >=3.9
License-File: LICENSE
Requires-Dist: pandas>=2.0
Requires-Dist: numpy>=1.23
Requires-Dist: scikit-learn>=1.3
Requires-Dist: xgboost>=1.7
Requires-Dist: statsforecast>=1.7.3
Requires-Dist: pydantic>=2.6
Requires-Dist: typer>=0.12
Requires-Dist: rich>=13.7
Requires-Dist: pvlib>=0.10
Requires-Dist: pyarrow>=14
Requires-Dist: pyyaml>=6
Requires-Dist: optuna>=3.4
Requires-Dist: prophet>=1.1.5; platform_machine != "arm64"
Requires-Dist: torch>=2.2; platform_machine != "arm64"
Requires-Dist: pytorch-lightning>=2.4; platform_machine != "arm64"
Requires-Dist: matplotlib>=3.7
Provides-Extra: dev
Requires-Dist: black>=23.0; extra == "dev"
Requires-Dist: ruff>=0.2; extra == "dev"
Requires-Dist: pytest>=7.0; extra == "dev"
Provides-Extra: docs
Requires-Dist: mkdocs>=1.5; extra == "docs"
Requires-Dist: mkdocs-material; extra == "docs"
Requires-Dist: mkdocstrings; extra == "docs"
Requires-Dist: mkdocstrings-python; extra == "docs"
Requires-Dist: pymdown-extensions; extra == "docs"
Dynamic: license-file
